moabb/__init__.py
moabb/benchmark.py
moabb/run.py
moabb/utils.py
moabb/analysis/__init__.py
moabb/analysis/meta_analysis.py
moabb/analysis/plotting.py
moabb/analysis/results.py
moabb/datasets/Lee2019.py
moabb/datasets/Weibo2014.py
moabb/datasets/Zhou2016.py
moabb/datasets/__init__.py
moabb/datasets/alex_mi.py
moabb/datasets/alphawaves.py
moabb/datasets/base.py
moabb/datasets/bbci_eeg_fnirs.py
moabb/datasets/beetl.py
moabb/datasets/bids_interface.py
moabb/datasets/bnci.py
moabb/datasets/braininvaders.py
moabb/datasets/castillos2023.py
moabb/datasets/download.py
moabb/datasets/dreyer2023.py
moabb/datasets/epfl.py
moabb/datasets/erpcore2021.py
moabb/datasets/fake.py
moabb/datasets/gigadb.py
moabb/datasets/hinss2021.py
moabb/datasets/huebner_llp.py
moabb/datasets/kojima2024a.py
moabb/datasets/kojima2024b.py
moabb/datasets/liu2024.py
moabb/datasets/mpi_mi.py
moabb/datasets/neiry.py
moabb/datasets/phmd_ml.py
moabb/datasets/physionet_mi.py
moabb/datasets/preprocessing.py
moabb/datasets/romani_bf2025_erp.py
moabb/datasets/schirrmeister2017.py
moabb/datasets/sosulski2019.py
moabb/datasets/ssvep_exo.py
moabb/datasets/ssvep_mamem.py
moabb/datasets/ssvep_nakanishi.py
moabb/datasets/ssvep_wang.py
moabb/datasets/stieger2021.py
moabb/datasets/summary_cvep.csv
moabb/datasets/summary_imagery.csv
moabb/datasets/summary_p300.csv
moabb/datasets/summary_rstate.csv
moabb/datasets/summary_ssvep.csv
moabb/datasets/thielen2015.py
moabb/datasets/thielen2021.py
moabb/datasets/upper_limb.py
moabb/datasets/utils.py
moabb/datasets/compound_dataset/__init__.py
moabb/datasets/compound_dataset/base.py
moabb/datasets/compound_dataset/bi_illiteracy.py
moabb/datasets/compound_dataset/utils.py
moabb/evaluations/__init__.py
moabb/evaluations/base.py
moabb/evaluations/evaluations.py
moabb/evaluations/splitters.py
moabb/evaluations/utils.py
moabb/paradigms/__init__.py
moabb/paradigms/base.py
moabb/paradigms/cvep.py
moabb/paradigms/fixed_interval_windows.py
moabb/paradigms/motor_imagery.py
moabb-1.4.3.dist-info/licenses/LICENSE
moabb-1.4.3.dist-info/METADATA
moabb-1.4.3.dist-info/WHEEL
moabb-1.4.3.dist-info/top_level.txt
moabb-1.4.3.dist-info/RECORD
