Metadata-Version: 2.4
Name: moabb
Version: 1.4.3
Summary: Mother of All BCI Benchmarks
Author: Alexandre Barachant, Vinay Jayaram
Maintainer-email: Sylvain Chevallier <sylvain.chevallier@universite-paris-saclay.fr>
License: BSD-3-Clause
Project-URL: homepage, https://moabb.neurotechx.com/docs/index.html
Project-URL: repository, https://github.com/NeuroTechX/moabb
Project-URL: documentation, https://moabb.neurotechx.com/docs/index.html
Keywords: eeg,datasets,reproducibility,bci,benchmark
Classifier: Development Status :: 4 - Beta
Classifier: Intended Audience :: Developers
Classifier: Intended Audience :: Science/Research
Classifier: Topic :: Scientific/Engineering :: Artificial Intelligence
Classifier: Topic :: Scientific/Engineering :: Medical Science Apps.
Classifier: Programming Language :: Python :: 3.11
Classifier: Programming Language :: Python :: 3.12
Classifier: Programming Language :: Python :: 3.13
Classifier: Programming Language :: Python :: 3.14
Requires-Python: >=3.10
License-File: LICENSE
Requires-Dist: numpy>=2.0
Requires-Dist: scipy>=1.9.3
Requires-Dist: mne>=1.10.0
Requires-Dist: pandas>=1.5.2
Requires-Dist: h5py>=3.10.0
Requires-Dist: matplotlib>=3.6.2
Requires-Dist: seaborn>=0.12.1
Requires-Dist: pyriemann>=0.9
Requires-Dist: PyYAML>=6.0
Requires-Dist: pooch>=1.6.0
Requires-Dist: requests>=2.28.1
Requires-Dist: urllib3>=1.26.15
Requires-Dist: tqdm>=4.64.1
Requires-Dist: coverage>=7.0.1
Requires-Dist: memory-profiler>=0.61.0
Requires-Dist: edflib-python>=1.0.6
Requires-Dist: edfio>=0.4.2
Requires-Dist: pytest>=8.3.5
Requires-Dist: mne-bids>=0.16
Requires-Dist: scikit-learn>=1.6
Provides-Extra: carbonemission
Requires-Dist: codecarbon>=2.1.4; extra == "carbonemission"
Provides-Extra: deeplearning
Requires-Dist: braindecode>=0.8.1; extra == "deeplearning"
Provides-Extra: optuna
Requires-Dist: optuna>=3.6.1; extra == "optuna"
Requires-Dist: optuna-integration>=3.6.0; extra == "optuna"
Provides-Extra: tests
Requires-Dist: pytest>=8.3.5; extra == "tests"
Requires-Dist: pytest-cov>=5.0.0; extra == "tests"
Requires-Dist: codecov>=2.1.0; extra == "tests"
Requires-Dist: pytest_cases>=3.0.0; extra == "tests"
Requires-Dist: pytest-xdist>=3.6.1; extra == "tests"
Provides-Extra: docs
Requires-Dist: Sphinx>=8.1.3; extra == "docs"
Requires-Dist: sphinx-gallery>=0.18.0; extra == "docs"
Requires-Dist: sphinx-bootstrap-theme>=0.8.1; extra == "docs"
Requires-Dist: pydata-sphinx-theme>=0.16.1; extra == "docs"
Requires-Dist: nbformat>=5.10.4; extra == "docs"
Requires-Dist: numpydoc>=1.8.0; extra == "docs"
Requires-Dist: myst-parser>=4.0.1; extra == "docs"
Requires-Dist: sphinx-design>=0.6.1; extra == "docs"
Requires-Dist: sphinx-rtd-theme>=3.0.2; extra == "docs"
Requires-Dist: sphinx_copybutton>=0.5.2; extra == "docs"
Requires-Dist: sphinxcontrib-bibtex>=2.6.3; extra == "docs"
Requires-Dist: sphinx-favicon>=1.0.1; extra == "docs"
Requires-Dist: mne-features>=0.3; extra == "docs"
Requires-Dist: snowballstemmer>=3.0.1; extra == "docs"
Requires-Dist: sphinx-sitemap; extra == "docs"
Provides-Extra: all
Requires-Dist: moabb[carbonemission]; extra == "all"
Requires-Dist: moabb[deeplearning]; extra == "all"
Requires-Dist: moabb[optuna]; extra == "all"
Requires-Dist: moabb[tests]; extra == "all"
Requires-Dist: moabb[docs]; extra == "all"
Dynamic: license-file
